clicks_util/Logger.py
clicks_util/__init__.py
clicks_util-0.0.2.dist-info/METADATA
clicks_util-0.0.2.dist-info/WHEEL
clicks_util-0.0.2.dist-info/top_level.txt
clicks_util-0.0.2.dist-info/RECORD
