Metadata-Version: 2.1
Name: clicks-util
Version: 0.0.2
Summary: Utilities for CuzImClicks
Author: CuzImClicks
Classifier: Programming Language :: Python :: 3
Classifier: Operating System :: OS Independent
Requires-Python: >=3.7
